easy_crud_repo_service/__init__.py
easy_crud_repo_service/model/__init__.py
easy_crud_repo_service/model/car.py
easy_crud_repo_service/model/order.py
easy_crud_repo_service/model/player.py
easy_crud_repo_service/model/team.py
easy_crud_repo_service/repo/__init__.py
easy_crud_repo_service/repo/connections/__init__.py
easy_crud_repo_service/repo/connections/builders.py
easy_crud_repo_service/repo/connections/get_connection_pool.py
easy_crud_repo_service/repo/crud_repo.py
easy_crud_repo_service-0.1.6.dist-info/METADATA
easy_crud_repo_service-0.1.6.dist-info/WHEEL
easy_crud_repo_service-0.1.6.dist-info/RECORD
