Metadata-Version: 2.1
Name: easy-crud-repo-service
Version: 0.1.6
Summary: 
Author: Smolke
Author-email: d.smolczynski1@gmail.com
Requires-Python: >=3.11,<4.0
Classifier: Programming Language :: Python :: 3
Classifier: Programming Language :: Python :: 3.11
Requires-Dist: dbm-database-service (>=0.2.5,<0.3.0)
Requires-Dist: easyvalid-data-validator (>=2.0.1,<3.0.0)
Requires-Dist: inflection (>=0.5.1,<0.6.0)
Requires-Dist: mysql-connector-python (>=8.0.33,<9.0.0)
Requires-Dist: python-dotenv (>=1.0.0,<2.0.0)
